timetrack/__init__.py
timetrack/cli.py
timetrack/core.py
timetrack/models.py
track_cli-0.1.0.dist-info/LICENSE
track_cli-0.1.0.dist-info/METADATA
track_cli-0.1.0.dist-info/WHEEL
track_cli-0.1.0.dist-info/entry_points.txt
track_cli-0.1.0.dist-info/top_level.txt
track_cli-0.1.0.dist-info/RECORD
