Metadata-Version: 2.1
Name: track-cli
Version: 0.1.0
Summary: A simple CLI tool for tracking time spent on tasks
Home-page: https://github.com/sakshamshil/Timetracker
Author: sakshamshil
Author-email: your.email@example.com
License: UNKNOWN
Project-URL: Bug Reports, https://github.com/sakshamshil/Timetracker/issues
Project-URL: Source, https://github.com/sakshamshil/Timetracker
Keywords: time tracking,productivity,cli,timesheet
Platform: UNKNOWN
Classifier: Development Status :: 4 - Beta
Classifier: Intended Audience :: Developers
Classifier: License :: OSI Approved :: MIT License
Classifier: Operating System :: OS Independent
Classifier: Programming Language :: Python :: 3
Classifier: Programming Language :: Python :: 3.8
Classifier: Programming Language :: Python :: 3.9
Classifier: Programming Language :: Python :: 3.10
Classifier: Programming Language :: Python :: 3.11
Classifier: Programming Language :: Python :: 3.12
Classifier: Topic :: Office/Business :: Scheduling
Classifier: Topic :: Utilities
Requires-Python: >=3.8
License-File: LICENSE
Requires-Dist: click (>=8.0.0)
Requires-Dist: openpyxl (>=3.0.0)
Requires-Dist: pandas (>=1.3.0)
Requires-Dist: pydantic (>=1.8.0)
Requires-Dist: python-dateutil (>=2.8.0)
